{
  "name": "Zoho Flow",
  "slug": "zoho-flow",
  "description": "Integration platform for connecting apps and automating workflows",
  "website": "https://www.zoho.com/flow/",
  "category": "development",
  "alternatives": [
    "Zapier",
    "Microsoft Power Automate",
    "IFTTT"
  ],
  "pricing": "Freemium",
  "company": "Zoho Corporation",
  "location": "Chennai",
  "faviconUrl": "https://www.zohowebstatic.com/sites/zweb/images/ogimage/flow-logo.png",
  "opengraph": {
    "last_updated": "2025-10-05T10:35:12.995Z",
    "title": "Zoho Flow: Integration platform for automating workflows",
    "description": "Zoho Flow is an integration platform that lets you automate your workflows regardless of your role or business.",
    "image": "https://www.zohowebstatic.com/sites/zweb/images/ogimage/flow-logo.png",
    "url": "https://www.zoho.com/flow/",
    "site_name": "Zoho",
    "type": "website",
    "twitter_title": "Zoho Flow: Integration platform for automating workflows",
    "twitter_description": "Zoho Flow is an integration platform that lets you automate your workflows regardless of your role or business.",
    "twitter_image": "https://www.zohowebstatic.com/sites/zweb/images/ogimage/flow-logo.png",
    "twitter_card": "summary",
    "twitter_site": "@zoho"
  }
}
